{
  "passengers": [
    {
      "fullname": "Steve",
      "id": 1,
      "checkedIn": true,
      "baggage": "none",
      "checkInDate": 1490742000000
    },
    {
      "id": 2,
      "fullname": "Sara",
      "checkedIn": false,
      "checkInDate": 1490642000000,
      "baggage": ""
    },
    {
      "id": 3,
      "fullname": "Yuki",
      "checkedIn": true,
      "checkInDate": 1490642000010,
      "baggage": ""
    },
    {
      "id": 4,
      "fullname": "Sara",
      "checkedIn": false,
      "checkInDate": 1490642000030,
      "baggage": ""
    }
  ]
}